sim/tut3_verilog/regincr/RegIncr.v
//========================================================================
// Registered Incrementer
//========================================================================
// This is a simple example of a module for a registered incrementer
// which combines a positive edge triggered register with a combinational
// +2 incrementer. We use flat register-transfer-level modeling.

`ifndef TUT3_VERILOG_REGINCR_REG_INCR_V
`define TUT3_VERILOG_REGINCR_REG_INCR_V

// You will need to uncomment this when you explore line tracing.
//
// `include "vc/trace.v"

module tut3_verilog_regincr_RegIncr
(
  input  logic       clk,
  input  logic       reset,
  input  logic [7:0] in_,
  output logic [7:0] out
);

  // Sequential logic

  logic [7:0] reg_out;
  always @( posedge clk ) begin
    if ( reset )
      reg_out <= 0;
    else
      reg_out <= in_;
  end
  
  logic [7:0] adder_out;
  always_comb begin
    adder_out = reg_out + 1;
  end
  assign out = adder_out;

  // You will need to uncomment this when you explore line tracing.
  //
  // `ifndef SYNTHESIS
  //
  // logic [`VC_TRACE_NBITS-1:0] str;
  // `VC_TRACE_BEGIN
  // begin
  //   $sformat( str, "%x (%x) %x", in_, reg_out, out );
  //   vc_trace.append_str( trace_str, str );
  // end
  // `VC_TRACE_END
  //
  // `endif /* SYNTHESIS */

endmodule

`endif /* TUT3_VERILOG_REGINCR_REG_INCR_V */

sim/tut3_verilog/regincr/regincr-adhoc-test.v
//========================================================================
// RegIncr Ad-Hoc Testing
//========================================================================

`include "RegIncr.v"

module top;

  // Clocking

  logic clk = 1;
  always #5 clk = ~clk;

  // Instaniate the design under test

  logic       reset = 1;
  logic [7:0] in_;
  logic [7:0] out;

  tut3_verilog_regincr_RegIncr reg_incr
  (
    .clk    (clk),
    .reset  (reset),
    .in_    (in_),
    .out    (out)
  );
  // Simulate the registered incrementer

  initial begin

    // Dump waveforms

    $dumpfile("regincr-adhoc-test.vcd");
    $dumpvars;

    // Reset

    #11;
    reset = 1'b0;

    // Cycle 1

    in_ = 8'h01;
    #10;
    $display( " cycle = 1: in = %x, out = %x", in_, out );

    // Cycle 2

    in_ = 8'h13;
    #10;
    $display( " cycle = 1: in = %x, out = %x", in_, out );

    // Cycle 3

    in_ = 8'h25;
    #10;
    $display( " cycle = 1: in = %x, out = %x", in_, out );

    // Cycle 4

    in_ = 8'h37;
    #10;
    $display( " cycle = 1: in = %x, out = %x", in_, out );

    $finish;
  end

endmodule

sim/tut3_verilog/regincr/regincr-adhoc-test.vcd
$date
	Tue Sep  3 15:40:00 2024
$end
$version
	Icarus Verilog
$end
$timescale
	1s
$end
$scope module top $end
$var wire 8 ! out [7:0] $end
$var reg 1 " clk $end
$var reg 8 # in_ [7:0] $end
$var reg 1 $ reset $end
$scope module reg_incr $end
$var wire 1 " clk $end
$var wire 8 % in_ [7:0] $end
$var wire 8 & out [7:0] $end
$var wire 1 $ reset $end
$var reg 8 ' adder_out [7:0] $end
$var reg 8 ( reg_out [7:0] $end
$upscope $end
$upscope $end
$enddefinitions $end
$comment Show the parameter values. $end
$dumpall
$end
#0
$dumpvars
bx (
bx '
bx &
bx %
1$
bx #
1"
bx !
$end
#5
0"
#10
b1 !
b1 &
b1 '
b0 (
1"
#11
b1 #
b1 %
0$
#15
0"
#20
b10 !
b10 &
b10 '
b1 (
1"
#21
b10011 #
b10011 %
#25
0"
#30
b10100 !
b10100 &
b10100 '
b10011 (
1"
#31
b100101 #
b100101 %
#35
0"
#40
b100110 !
b100110 &
b100110 '
b100101 (
1"
#41
b110111 #
b110111 %
#45
0"
#50
b111000 !
b111000 &
b111000 '
b110111 (
1"
